{
    "errors": [],
    "items": [
        {
            "application": {
                "id": 322931,
                "name": "Android UI Integration Test App"
            },
            "date": "2011-10-15 00:01:14+0000",
            "entity": {
                "comments": 1,
                "key": "http://entity1.com",
                "likes": 0,
                "name": "First Entity",
                "shares": 0,
                "views": 0
            },
            "id": 245658,
            "lat": 24.338342174336155,
            "lng": 68.132282375329,
            "share_location": 1,
            "text": "POST comment #0",
            "user": {
                "city": null,
                "first_name": null,
                "id": 52640320,
                "last_name": null,
                "meta": null,
                "small_image_uri": null,
                "state": null,
                "third_party_auth": [],
                "username": "User52640320"
            }
        },
        {
            "application": {
                "id": 322931,
                "name": "Android UI Integration Test App"
            },
            "date": "2011-10-15 00:01:14+0000",
            "entity": {
                "comments": 2,
                "key": "http://entity1.com",
                "likes": 0,
                "name": "First Entity",
                "shares": 0,
                "views": 0
            },
            "id": 245659,
            "lat": 18.5584344481741,
            "lng": 85.52172211658844,
            "share_location": 1,
            "text": "POST comment #1",
            "user": {
                "city": null,
                "first_name": null,
                "id": 52640320,
                "last_name": null,
                "meta": null,
                "small_image_uri": null,
                "state": null,
                "third_party_auth": [],
                "username": "User52640320"
            }
        },
        {
            "application": {
                "id": 322931,
                "name": "Android UI Integration Test App"
            },
            "date": "2011-10-15 00:01:14+0000",
            "entity": {
                "comments": 3,
                "key": "http://entity1.com",
                "likes": 0,
                "name": "First Entity",
                "shares": 0,
                "views": 0
            },
            "id": 245660,
            "lat": 63.29633256095452,
            "lng": 70.27655106678809,
            "share_location": 1,
            "text": "POST comment #2",
            "user": {
                "city": null,
                "first_name": null,
                "id": 52640320,
                "last_name": null,
                "meta": null,
                "small_image_uri": null,
                "state": null,
                "third_party_auth": [],
                "username": "User52640320"
            }
        },
        {
            "application": {
                "id": 322931,
                "name": "Android UI Integration Test App"
            },
            "date": "2011-10-15 00:01:15+0000",
            "entity": {
                "comments": 4,
                "key": "http://entity1.com",
                "likes": 0,
                "name": "First Entity",
                "shares": 0,
                "views": 0
            },
            "id": 245661,
            "lat": 0.6817117660880934,
            "lng": 75.22051918653187,
            "share_location": 1,
            "text": "POST comment #3",
            "user": {
                "city": null,
                "first_name": null,
                "id": 52640320,
                "last_name": null,
                "meta": null,
                "small_image_uri": null,
                "state": null,
                "third_party_auth": [],
                "username": "User52640320"
            }
        },
        {
            "application": {
                "id": 322931,
                "name": "Android UI Integration Test App"
            },
            "date": "2011-10-15 00:01:15+0000",
            "entity": {
                "comments": 5,
                "key": "http://entity1.com",
                "likes": 0,
                "name": "First Entity",
                "shares": 0,
                "views": 0
            },
            "id": 245662,
            "lat": 20.060057763166654,
            "lng": 0.3158236091434008,
            "share_location": 1,
            "text": "POST comment #4",
            "user": {
                "city": null,
                "first_name": null,
                "id": 52640320,
                "last_name": null,
                "meta": null,
                "small_image_uri": null,
                "state": null,
                "third_party_auth": [],
                "username": "User52640320"
            }
        },
        {
            "application": {
                "id": 322931,
                "name": "Android UI Integration Test App"
            },
            "date": "2011-10-15 00:01:15+0000",
            "entity": {
                "comments": 6,
                "key": "http://entity1.com",
                "likes": 0,
                "name": "First Entity",
                "shares": 0,
                "views": 0
            },
            "id": 245663,
            "lat": 71.25548623373899,
            "lng": 11.834384837737666,
            "share_location": 1,
            "text": "POST comment #5",
            "user": {
                "city": null,
                "first_name": null,
                "id": 52640320,
                "last_name": null,
                "meta": null,
                "small_image_uri": null,
                "state": null,
                "third_party_auth": [],
                "username": "User52640320"
            }
        },
        {
            "application": {
                "id": 322931,
                "name": "Android UI Integration Test App"
            },
            "date": "2011-10-15 00:01:15+0000",
            "entity": {
                "comments": 7,
                "key": "http://entity1.com",
                "likes": 0,
                "name": "First Entity",
                "shares": 0,
                "views": 0
            },
            "id": 245664,
            "lat": 62.23736913058965,
            "lng": 8.904241995927155,
            "share_location": 1,
            "text": "POST comment #6",
            "user": {
                "city": null,
                "first_name": null,
                "id": 52640320,
                "last_name": null,
                "meta": null,
                "small_image_uri": null,
                "state": null,
                "third_party_auth": [],
                "username": "User52640320"
            }
        },
        {
            "application": {
                "id": 322931,
                "name": "Android UI Integration Test App"
            },
            "date": "2011-10-15 00:01:15+0000",
            "entity": {
                "comments": 8,
                "key": "http://entity1.com",
                "likes": 0,
                "name": "First Entity",
                "shares": 0,
                "views": 0
            },
            "id": 245665,
            "lat": 5.554476109565987,
            "lng": 85.1021499454974,
            "share_location": 1,
            "text": "POST comment #7",
            "user": {
                "city": null,
                "first_name": null,
                "id": 52640320,
                "last_name": null,
                "meta": null,
                "small_image_uri": null,
                "state": null,
                "third_party_auth": [],
                "username": "User52640320"
            }
        },
        {
            "application": {
                "id": 322931,
                "name": "Android UI Integration Test App"
            },
            "date": "2011-10-15 00:01:15+0000",
            "entity": {
                "comments": 9,
                "key": "http://entity1.com",
                "likes": 0,
                "name": "First Entity",
                "shares": 0,
                "views": 0
            },
            "id": 245666,
            "lat": 73.21247762147,
            "lng": 21.2693943746298,
            "share_location": 1,
            "text": "POST comment #8",
            "user": {
                "city": null,
                "first_name": null,
                "id": 52640320,
                "last_name": null,
                "meta": null,
                "small_image_uri": null,
                "state": null,
                "third_party_auth": [],
                "username": "User52640320"
            }
        },
        {
            "application": {
                "id": 322931,
                "name": "Android UI Integration Test App"
            },
            "date": "2011-10-15 00:01:15+0000",
            "entity": {
                "comments": 10,
                "key": "http://entity1.com",
                "likes": 0,
                "name": "First Entity",
                "shares": 0,
                "views": 0
            },
            "id": 245667,
            "lat": 76.6696629808717,
            "lng": 30.559902247243215,
            "share_location": 1,
            "text": "POST comment #9",
            "user": {
                "city": null,
                "first_name": null,
                "id": 52640320,
                "last_name": null,
                "meta": null,
                "small_image_uri": null,
                "state": null,
                "third_party_auth": [],
                "username": "User52640320"
            }
        }
    ]
}